AUTHORS.rst
CONTRIBUTING.rst
HISTORY.rst
LICENSE
MANIFEST.in
README.rst
setup.cfg
setup.py
docs/Makefile
docs/authors.rst
docs/conf.py
docs/contributing.rst
docs/history.rst
docs/index.rst
docs/installation.rst
docs/make.bat
docs/readme.rst
docs/usage.rst
epic_trials/__init__.py
epic_trials/epic_trials.py
epic_trials.egg-info/PKG-INFO
epic_trials.egg-info/SOURCES.txt
epic_trials.egg-info/dependency_links.txt
epic_trials.egg-info/not-zip-safe
epic_trials.egg-info/top_level.txt
tests/__init__.py
tests/test_epic_trials.py