Metadata-Version: 1.2
Name: epic-trials
Version: 0.0.1
Summary: Trials for the EPIC labs of the Concrete, Soil and Material
Home-page: https://github.com/jorgeav527/epic_trials
Author: Jorge Ramiro Alarcon Vargas
Author-email: jorgeav527@gmail.com
License: MIT license
Keywords: epic_trials
Platform: UNKNOWN
Classifier: Development Status :: 2 - Pre-Alpha
Classifier: Intended Audience :: Developers
Classifier: License :: OSI Approved :: MIT License
Classifier: Natural Language :: English
Classifier: Programming Language :: Python :: 3
Classifier: Programming Language :: Python :: 3.6
Classifier: Programming Language :: Python :: 3.7
Classifier: Programming Language :: Python :: 3.8
Requires-Python: >=3.6
